astroglam/MCMC_routines.py
astroglam/__init__.py
astroglam/atomic_data.py
astroglam/cooling_rates.py
astroglam/emission_models.py
astroglam/empirical.py
astroglam/ion_structure.py
astroglam-0.1.0.dist-info/LICENSE
astroglam-0.1.0.dist-info/METADATA
astroglam-0.1.0.dist-info/WHEEL
astroglam-0.1.0.dist-info/top_level.txt
astroglam-0.1.0.dist-info/RECORD
