Metadata-Version: 2.1
Name: astroglam
Version: 0.1.0
Summary: A code to leverage ALMA and JWST data to infer the gas density, metallicity, and burstiness of galaxies.
Home-page: https://github.com/lvallini/
Author: Livia Vallini
Author-email: Livia Vallini <livia.vallini@inaf.it>
Project-URL: Homepage, https://github.com/lvallini/MCMC_galaxyline_analyzer
Project-URL: Issues, https://github.com/lvallini/MCMC_galaxyline_analyzer
Classifier: Programming Language :: Python :: 3
Classifier: License :: OSI Approved :: MIT License
Classifier: Operating System :: OS Independent
Classifier: Topic :: Scientific/Engineering :: Astronomy
Classifier: Intended Audience :: Science/Research
Requires-Python: >=3.9, <4
License-File: LICENSE
Requires-Dist: contourpy >=1.2.0
Requires-Dist: corner >=2.2.2
Requires-Dist: cycler >=0.11.0
Requires-Dist: emcee >=3.1.6
Requires-Dist: fonttools >=4.51.0
Requires-Dist: h5py >=3.11.0
Requires-Dist: kiwisolver >=1.4.4
Requires-Dist: matplotlib >=3.9.2
Requires-Dist: numpy <2.0
Requires-Dist: packaging ==24.1
Requires-Dist: pillow >=10.4.0
Requires-Dist: pip >=24.2
Requires-Dist: PyNeb >=1.1.16
Requires-Dist: pyparsing >=3.1.2
Requires-Dist: python-dateutil >=2.9.0.post0
Requires-Dist: scipy >=1.13.1
Requires-Dist: setuptools >=59
Requires-Dist: six >=1.16.0
Requires-Dist: tornado >=6.4.1
Requires-Dist: unicodedata2 >=15.1.0
Requires-Dist: wheel >=0.44.0
Requires-Dist: tqdm >=4.66.5
